dcclib_cli/__init__.py
dcclib_cli/cli.py
dcclib_cli/commands/__init__.py
dcclib_cli/commands/cmd_convert.py
dcclib_cli/commands/cmd_signature.py
dcclib_cli/commands/cmd_transform.py
dcclib_cli/commands/output.py
dcclib_cli/commands/extract/__init__.py
dcclib_cli/commands/extract/cmd_extract.py
dcclib_cli/commands/extract/cmd_files.py
dcclib_cli/commands/extract/cmd_formulae.py
dcclib_cli/commands/validate/__init__.py
dcclib_cli/commands/validate/cmd_schematron.py
dcclib_cli/commands/validate/cmd_validate.py
dcclib_cli/commands/validate/cmd_xsd.py
dcclib_cli-0.3.0.dist-info/METADATA
dcclib_cli-0.3.0.dist-info/WHEEL
dcclib_cli-0.3.0.dist-info/entry_points.txt
dcclib_cli-0.3.0.dist-info/RECORD
